excel/__init__.py
excel/_pandas_integration.py
excel/report.py
excel/common/constants.py
excel/common/exceptions.py
excel/common/util.py
excel/format/__init__.py
excel/format/formats.py
excel/format/formatters.py
excel/format/infer.py
excel/format/type_checkers.py
excel/write/__init__.py
excel/write/chart.py
excel/write/sheet.py
pandas_excel-0.2.0.dist-info/METADATA
pandas_excel-0.2.0.dist-info/WHEEL
pandas_excel-0.2.0.dist-info/top_level.txt
pandas_excel-0.2.0.dist-info/RECORD
