Metadata-Version: 2.1
Name: pandas-excel
Version: 0.2.0
Summary: quickly turn pandas dataframes into shareable Excel reports
Home-page: https://github.com/christopher-hacker/pandas-excel
Author: Christopher Hacker
Author-email: hackerlikecomputer@gmail.com
License: UNKNOWN
Platform: UNKNOWN
Requires-Dist: pandas
Requires-Dist: XlsxWriter
Requires-Dist: setuptools
